{
	"info": {
		"_postman_id": "5be95a98-1838-4ec9-98d5-228b1890a195",
		"name": "Metavagas",
		"schema": "https://schema.getpostman.com/json/collection/v2.1.0/collection.json",
		"_exporter_id": "30233660"
	},
	"item": [
		{
			"name": "Vacancies",
			"item": [
				{
					"name": "Vacancy - Get All",
					"event": [
						{
							"listen": "test",
							"script": {
								"exec": [
									""
								],
								"type": "text/javascript"
							}
						}
					],
					"protocolProfileBehavior": {
						"followRedirects": true,
						"disableUrlEncoding": false,
						"disableCookies": false
					},
					"request": {
						"auth": {
							"type": "noauth"
						},
						"method": "GET",
						"header": [],
						"url": {
							"raw": "{{host}}/vacancies",
							"host": [
								"{{host}}"
							],
							"path": [
								"vacancies"
							],
							"query": [
								{
									"key": "vacancyRole",
									"value": "Back",
									"disabled": true
								},
								{
									"key": "wageMin",
									"value": "2000",
									"disabled": true
								},
								{
									"key": "wageMax",
									"value": "10000",
									"disabled": true
								},
								{
									"key": "location",
									"value": "São",
									"disabled": true
								},
								{
									"key": "vacancyTypes[]",
									"value": "Remoto",
									"disabled": true
								},
								{
									"key": "vacancyTypes[]",
									"value": "Presencial",
									"disabled": true
								},
								{
									"key": "technologyIds[]",
									"value": "3",
									"disabled": true
								},
								{
									"key": "technologyIds[]",
									"value": "4",
									"disabled": true
								},
								{
									"key": "technologyIds[]",
									"value": "1",
									"disabled": true
								},
								{
									"key": "limit",
									"value": "16",
									"disabled": true
								},
								{
									"key": "page",
									"value": "1",
									"disabled": true
								}
							]
						}
					},
					"response": []
				},
				{
					"name": "Vacancy - GetById",
					"event": [
						{
							"listen": "test",
							"script": {
								"exec": [
									""
								],
								"type": "text/javascript"
							}
						}
					],
					"protocolProfileBehavior": {
						"followRedirects": true,
						"disableUrlEncoding": false,
						"disableCookies": false
					},
					"request": {
						"auth": {
							"type": "bearer",
							"bearer": [
								{
									"key": "token",
									"value": "{{token}}",
									"type": "string"
								}
							]
						},
						"method": "GET",
						"header": [],
						"url": {
							"raw": "{{host}}/vacancies/2",
							"host": [
								"{{host}}"
							],
							"path": [
								"vacancies",
								"2"
							]
						}
					},
					"response": []
				},
				{
					"name": "Vacancy - Delete",
					"event": [
						{
							"listen": "test",
							"script": {
								"exec": [
									""
								],
								"type": "text/javascript"
							}
						}
					],
					"protocolProfileBehavior": {
						"followRedirects": true,
						"disableUrlEncoding": false,
						"disableCookies": false
					},
					"request": {
						"auth": {
							"type": "bearer",
							"bearer": [
								{
									"key": "token",
									"value": "{{token}}",
									"type": "string"
								}
							]
						},
						"method": "DELETE",
						"header": [],
						"url": {
							"raw": "{{host}}/vacancies/1",
							"host": [
								"{{host}}"
							],
							"path": [
								"vacancies",
								"1"
							]
						}
					},
					"response": []
				},
				{
					"name": "Vacancy - Create",
					"event": [
						{
							"listen": "test",
							"script": {
								"exec": [
									""
								],
								"type": "text/javascript"
							}
						}
					],
					"protocolProfileBehavior": {
						"followRedirects": true,
						"disableUrlEncoding": false,
						"disableCookies": false
					},
					"request": {
						"auth": {
							"type": "bearer",
							"bearer": [
								{
									"key": "token",
									"value": "{{token}}",
									"type": "string"
								}
							]
						},
						"method": "POST",
						"header": [],
						"body": {
							"mode": "raw",
							"raw": "{\n    \"companyId\": 2,\n    \"vacancyRole\": \"Desenvolvedor FullStack Java\",\n    \"wage\": 8000,\n    \"location\": \"Uberlândia\",\n    \"vacancyType\": \"Remoto\",\n    \"vacancyDescription\": \"Desenvolvedor FullStack para projeto web.\",\n    \"level\": \"Junior\",\n    \"technologyIds\": [1,2,3,14]\n}",
							"options": {
								"raw": {
									"language": "json"
								}
							}
						},
						"url": {
							"raw": "{{host}}/vacancies",
							"host": [
								"{{host}}"
							],
							"path": [
								"vacancies"
							]
						}
					},
					"response": []
				},
				{
					"name": "Vacancy - Update",
					"event": [
						{
							"listen": "test",
							"script": {
								"exec": [
									""
								],
								"type": "text/javascript"
							}
						}
					],
					"protocolProfileBehavior": {
						"followRedirects": true,
						"disableUrlEncoding": false,
						"disableCookies": false
					},
					"request": {
						"auth": {
							"type": "bearer",
							"bearer": [
								{
									"key": "token",
									"value": "{{token}}",
									"type": "string"
								}
							]
						},
						"method": "PATCH",
						"header": [],
						"body": {
							"mode": "raw",
							"raw": "{\n    \"vacancyRole\": \"Desenvolvedor Back End\"\n}",
							"options": {
								"raw": {
									"language": "json"
								}
							}
						},
						"url": {
							"raw": "{{host}}/vacancies/2",
							"host": [
								"{{host}}"
							],
							"path": [
								"vacancies",
								"2"
							]
						}
					},
					"response": []
				}
			]
		},
		{
			"name": "Companies",
			"item": [
				{
					"name": "Company - Create",
					"event": [
						{
							"listen": "test",
							"script": {
								"exec": [
									""
								],
								"type": "text/javascript"
							}
						}
					],
					"protocolProfileBehavior": {
						"followRedirects": true,
						"disableUrlEncoding": false,
						"disableCookies": false
					},
					"request": {
						"auth": {
							"type": "bearer",
							"bearer": [
								{
									"key": "token",
									"value": "{{token}}",
									"type": "string"
								}
							]
						},
						"method": "POST",
						"header": [],
						"body": {
							"mode": "raw",
							"raw": "{\n  \"name\": \"Arnia Teste\",\n  \"city\": \"Belo Horizonte\",\n  \"state\": \"MG\",\n  \"address\": \"Av. do Contorno, 2905\",\n  \"foundedAt\": \"2013-03-30\",\n  \"description\": \"Líder em desenvolvimento de sistemas para empresas nacionais.\"\n}",
							"options": {
								"raw": {
									"language": "json"
								}
							}
						},
						"url": {
							"raw": "{{host}}/companies",
							"host": [
								"{{host}}"
							],
							"path": [
								"companies"
							]
						}
					},
					"response": []
				},
				{
					"name": "Company - Delete",
					"event": [
						{
							"listen": "test",
							"script": {
								"exec": [
									""
								],
								"type": "text/javascript"
							}
						}
					],
					"protocolProfileBehavior": {
						"followRedirects": true,
						"disableUrlEncoding": false,
						"disableCookies": false
					},
					"request": {
						"auth": {
							"type": "bearer",
							"bearer": [
								{
									"key": "token",
									"value": "{{token}}",
									"type": "string"
								}
							]
						},
						"method": "DELETE",
						"header": [],
						"url": {
							"raw": "{{host}}/companies/4",
							"host": [
								"{{host}}"
							],
							"path": [
								"companies",
								"4"
							]
						}
					},
					"response": []
				},
				{
					"name": "Company - Update",
					"event": [
						{
							"listen": "test",
							"script": {
								"exec": [
									""
								],
								"type": "text/javascript"
							}
						}
					],
					"protocolProfileBehavior": {
						"followRedirects": true,
						"disableUrlEncoding": false,
						"disableCookies": false
					},
					"request": {
						"auth": {
							"type": "bearer",
							"bearer": [
								{
									"key": "token",
									"value": "{{token}}",
									"type": "string"
								}
							]
						},
						"method": "PATCH",
						"header": [],
						"body": {
							"mode": "raw",
							"raw": "{\n  \"name\": \"Arnia Dev\"\n}",
							"options": {
								"raw": {
									"language": "json"
								}
							}
						},
						"url": {
							"raw": "{{host}}/companies/3",
							"host": [
								"{{host}}"
							],
							"path": [
								"companies",
								"3"
							]
						}
					},
					"response": []
				},
				{
					"name": "Company - GetAll",
					"event": [
						{
							"listen": "test",
							"script": {
								"exec": [
									""
								],
								"type": "text/javascript"
							}
						}
					],
					"protocolProfileBehavior": {
						"followRedirects": true,
						"disableUrlEncoding": false,
						"disableCookies": false
					},
					"request": {
						"auth": {
							"type": "bearer",
							"bearer": [
								{
									"key": "token",
									"value": "{{token}}",
									"type": "string"
								}
							]
						},
						"method": "GET",
						"header": [],
						"url": {
							"raw": "{{host}}/companies",
							"host": [
								"{{host}}"
							],
							"path": [
								"companies"
							],
							"query": [
								{
									"key": "name",
									"value": "Arnia",
									"disabled": true
								}
							]
						}
					},
					"response": []
				},
				{
					"name": "Company - GetById",
					"event": [
						{
							"listen": "test",
							"script": {
								"exec": [
									""
								],
								"type": "text/javascript"
							}
						}
					],
					"protocolProfileBehavior": {
						"followRedirects": true,
						"disableUrlEncoding": false,
						"disableCookies": false
					},
					"request": {
						"auth": {
							"type": "bearer",
							"bearer": [
								{
									"key": "token",
									"value": "{{token}}",
									"type": "string"
								}
							]
						},
						"method": "GET",
						"header": [],
						"url": {
							"raw": "{{host}}/companies/1",
							"host": [
								"{{host}}"
							],
							"path": [
								"companies",
								"1"
							]
						}
					},
					"response": []
				}
			]
		},
		{
			"name": "Technology",
			"item": [
				{
					"name": "Technology - Create",
					"event": [
						{
							"listen": "test",
							"script": {
								"exec": [
									""
								],
								"type": "text/javascript"
							}
						}
					],
					"protocolProfileBehavior": {
						"followRedirects": true,
						"disableUrlEncoding": false,
						"disableCookies": false
					},
					"request": {
						"auth": {
							"type": "bearer",
							"bearer": [
								{
									"key": "token",
									"value": "{{token}}",
									"type": "string"
								}
							]
						},
						"method": "POST",
						"header": [],
						"body": {
							"mode": "raw",
							"raw": "{\n  \"tecName\": \"Flutter\",\n  \"creatorsName\": \"Mary\"\n}",
							"options": {
								"raw": {
									"language": "json"
								}
							}
						},
						"url": {
							"raw": "{{host}}/technologies",
							"host": [
								"{{host}}"
							],
							"path": [
								"technologies"
							]
						}
					},
					"response": []
				},
				{
					"name": "Technology - Delete",
					"event": [
						{
							"listen": "test",
							"script": {
								"exec": [
									""
								],
								"type": "text/javascript"
							}
						}
					],
					"protocolProfileBehavior": {
						"followRedirects": true,
						"disableUrlEncoding": false,
						"disableCookies": false
					},
					"request": {
						"auth": {
							"type": "bearer",
							"bearer": [
								{
									"key": "token",
									"value": "{{token}}",
									"type": "string"
								}
							]
						},
						"method": "DELETE",
						"header": [],
						"url": {
							"raw": "{{host}}/technologies/13",
							"host": [
								"{{host}}"
							],
							"path": [
								"technologies",
								"13"
							]
						}
					},
					"response": []
				},
				{
					"name": "Technology - Update",
					"event": [
						{
							"listen": "test",
							"script": {
								"exec": [
									""
								],
								"type": "text/javascript"
							}
						}
					],
					"protocolProfileBehavior": {
						"followRedirects": true,
						"disableUrlEncoding": false,
						"disableCookies": false
					},
					"request": {
						"auth": {
							"type": "bearer",
							"bearer": [
								{
									"key": "token",
									"value": "{{token}}",
									"type": "string"
								}
							]
						},
						"method": "PATCH",
						"header": [],
						"body": {
							"mode": "raw",
							"raw": "{\n  \"creatorsName\": \"Marco\"\n}",
							"options": {
								"raw": {
									"language": "json"
								}
							}
						},
						"url": {
							"raw": "{{host}}/technologies/14",
							"host": [
								"{{host}}"
							],
							"path": [
								"technologies",
								"14"
							]
						}
					},
					"response": []
				},
				{
					"name": "Technology - GetAll",
					"event": [
						{
							"listen": "test",
							"script": {
								"exec": [
									""
								],
								"type": "text/javascript"
							}
						}
					],
					"protocolProfileBehavior": {
						"followRedirects": true,
						"disableUrlEncoding": false,
						"disableCookies": false
					},
					"request": {
						"auth": {
							"type": "noauth"
						},
						"method": "GET",
						"header": [],
						"url": {
							"raw": "{{host}}/technologies",
							"host": [
								"{{host}}"
							],
							"path": [
								"technologies"
							]
						}
					},
					"response": []
				},
				{
					"name": "Technology - GetById",
					"event": [
						{
							"listen": "test",
							"script": {
								"exec": [
									""
								],
								"type": "text/javascript"
							}
						}
					],
					"protocolProfileBehavior": {
						"followRedirects": true,
						"disableUrlEncoding": false,
						"disableCookies": false
					},
					"request": {
						"auth": {
							"type": "bearer",
							"bearer": [
								{
									"key": "token",
									"value": "{{token}}",
									"type": "string"
								}
							]
						},
						"method": "GET",
						"header": [],
						"url": {
							"raw": "{{host}}/technologies/1",
							"host": [
								"{{host}}"
							],
							"path": [
								"technologies",
								"1"
							]
						}
					},
					"response": []
				}
			]
		},
		{
			"name": "Users",
			"item": [
				{
					"name": "Users - Get All",
					"event": [
						{
							"listen": "test",
							"script": {
								"exec": [
									""
								],
								"type": "text/javascript"
							}
						}
					],
					"protocolProfileBehavior": {
						"followRedirects": true,
						"disableUrlEncoding": false,
						"disableCookies": false
					},
					"request": {
						"auth": {
							"type": "bearer",
							"bearer": [
								{
									"key": "token",
									"value": "{{token}}",
									"type": "string"
								}
							]
						},
						"method": "GET",
						"header": [],
						"url": {
							"raw": "{{host}}/users",
							"host": [
								"{{host}}"
							],
							"path": [
								"users"
							]
						}
					},
					"response": []
				},
				{
					"name": "Users - GetById",
					"event": [
						{
							"listen": "test",
							"script": {
								"exec": [
									""
								],
								"type": "text/javascript"
							}
						}
					],
					"protocolProfileBehavior": {
						"followRedirects": true,
						"disableUrlEncoding": false,
						"disableCookies": false
					},
					"request": {
						"auth": {
							"type": "bearer",
							"bearer": [
								{
									"key": "token",
									"value": "{{token}}",
									"type": "string"
								}
							]
						},
						"method": "GET",
						"header": [
							{
								"key": "User-Agent",
								"value": "insomnia/9.1.1"
							}
						],
						"url": {
							"raw": "{{host}}/users/2",
							"host": [
								"{{host}}"
							],
							"path": [
								"users",
								"2"
							]
						}
					},
					"response": []
				},
				{
					"name": "Users - Delete",
					"event": [
						{
							"listen": "test",
							"script": {
								"exec": [
									""
								],
								"type": "text/javascript"
							}
						}
					],
					"protocolProfileBehavior": {
						"followRedirects": true,
						"disableUrlEncoding": false,
						"disableCookies": false
					},
					"request": {
						"auth": {
							"type": "bearer",
							"bearer": [
								{
									"key": "token",
									"value": "{{token}}",
									"type": "string"
								}
							]
						},
						"method": "DELETE",
						"header": [],
						"url": {
							"raw": "{{host}}/users/1",
							"host": [
								"{{host}}"
							],
							"path": [
								"users",
								"1"
							]
						}
					},
					"response": []
				},
				{
					"name": "Users - Update",
					"event": [
						{
							"listen": "test",
							"script": {
								"exec": [
									""
								],
								"type": "text/javascript"
							}
						}
					],
					"protocolProfileBehavior": {
						"followRedirects": true,
						"disableUrlEncoding": false,
						"disableCookies": false
					},
					"request": {
						"auth": {
							"type": "bearer",
							"bearer": [
								{
									"key": "token",
									"value": "{{token}}",
									"type": "string"
								}
							]
						},
						"method": "PATCH",
						"header": [],
						"body": {
							"mode": "raw",
							"raw": "{\n  \"name\": \"Jenifer Silva\"\n}",
							"options": {
								"raw": {
									"language": "json"
								}
							}
						},
						"url": {
							"raw": "{{host}}/users/2",
							"host": [
								"{{host}}"
							],
							"path": [
								"users",
								"2"
							]
						}
					},
					"response": []
				}
			]
		},
		{
			"name": "Auth",
			"item": [
				{
					"name": "Auth - Me",
					"event": [
						{
							"listen": "test",
							"script": {
								"exec": [
									""
								],
								"type": "text/javascript"
							}
						}
					],
					"protocolProfileBehavior": {
						"followRedirects": true,
						"disableUrlEncoding": false,
						"disableCookies": false
					},
					"request": {
						"auth": {
							"type": "bearer",
							"bearer": [
								{
									"key": "token",
									"value": "{{token}}",
									"type": "string"
								}
							]
						},
						"method": "GET",
						"header": [],
						"url": {
							"raw": "{{host}}/auth/me",
							"host": [
								"{{host}}"
							],
							"path": [
								"auth",
								"me"
							]
						}
					},
					"response": []
				},
				{
					"name": "Auth - Login",
					"event": [
						{
							"listen": "test",
							"script": {
								"exec": [
									"if (pm.response.code >= 200 && pm.response.code <= 299) {",
									"    var jsonData = pm.response.json();",
									"    pm.globals.set(\"token\", jsonData.token);",
									"}"
								],
								"type": "text/javascript"
							}
						}
					],
					"protocolProfileBehavior": {
						"followRedirects": true,
						"disableUrlEncoding": false,
						"disableCookies": false
					},
					"request": {
						"method": "POST",
						"header": [],
						"body": {
							"mode": "raw",
							"raw": "{\n  \"email\": \"mary@email.com\",\n  \"password\": \"senha@123\"\n}",
							"options": {
								"raw": {
									"language": "json"
								}
							}
						},
						"url": {
							"raw": "{{host}}/auth/login",
							"host": [
								"{{host}}"
							],
							"path": [
								"auth",
								"login"
							]
						}
					},
					"response": []
				},
				{
					"name": "Auth - Register",
					"event": [
						{
							"listen": "test",
							"script": {
								"exec": [
									""
								],
								"type": "text/javascript"
							}
						}
					],
					"protocolProfileBehavior": {
						"followRedirects": true,
						"disableUrlEncoding": false,
						"disableCookies": false
					},
					"request": {
						"method": "POST",
						"header": [],
						"body": {
							"mode": "raw",
							"raw": "{\n  \"name\": \"Mary Silva\",\n  \"email\": \"mary@email.com\",\n  \"password\": \"senha@123\",\n  \"role\": \"admin\"\n}",
							"options": {
								"raw": {
									"language": "json"
								}
							}
						},
						"url": {
							"raw": "{{host}}/auth/register",
							"host": [
								"{{host}}"
							],
							"path": [
								"auth",
								"register"
							]
						}
					},
					"response": []
				}
			]
		}
	]
}